{
    "latest-catalyst-master": [
        {
            "group": "catalyst-master",
            "site": "gitlab-ci",
            "buildname": "[fedora33]"
        },
        {
            "group": "catalyst-master",
            "site": "gitlab-ci",
            "buildname": "[fedora33_replay]"
        },
        {
            "group": "catalyst-master",
            "site": "gitlab-ci",
            "buildname": "[fedora33_mpi_replay]"
        },
        {
            "group": "catalyst-master",
            "site": "gitlab-ci",
            "buildname": "[macos_arm64_replay]"
        },
        {
            "group": "catalyst-master",
            "site": "gitlab-ci",
            "buildname": "[macos_x86_64_replay]"
        },
        {
            "group": "catalyst-master",
            "site": "gitlab-ci",
            "buildname": "[windows_vs2022_mpi_replay]"
        },
        {
            "group": "catalyst-master",
            "site": "gitlab-ci",
            "buildname": "[windows_vs2022_replay]"
        }
    ]
}
